fumigate/__init__.py
fumigate/fumes.py
fumigate-0.1.8.dist-info/METADATA
fumigate-0.1.8.dist-info/WHEEL
fumigate-0.1.8.dist-info/top_level.txt
fumigate-0.1.8.dist-info/RECORD
