Metadata-Version: 2.1
Name: fumigate
Version: 0.1.8
Summary: Fumigate text
Home-page: https://fumigate.readthedocs.io/
Author: Gagandeep Prasad
Author-email: gagandeepprasad09@gmail.com
License: MIT
Platform: UNKNOWN
Classifier: Intended Audience :: Developers
Classifier: License :: OSI Approved :: MIT License
Classifier: Programming Language :: Python
Classifier: Programming Language :: Python :: 3
Classifier: Programming Language :: Python :: 3.6
Classifier: Programming Language :: Python :: 3.7
Classifier: Programming Language :: Python :: 3.8
Classifier: Programming Language :: Python :: 3.9
Classifier: Operating System :: OS Independent
Requires-Dist: numpy
Requires-Dist: nltk
